confme/__init__.py
confme/annotation.py
confme/core/__init__.py
confme/core/argument_overwrite.py
confme/core/base_config.py
confme/core/env_overwrite.py
confme/pylintrc
confme/source_backend/__init__.py
confme/source_backend/backend_base.py
confme/source_backend/backend_yaml.py
confme/utils/__init__.py
confme/utils/base_exception.py
confme/utils/deprecated.py
confme/utils/dict_util.py
confme/utils/typing.py
confme-2.0.4.dist-info/LICENSE
confme-2.0.4.dist-info/METADATA
confme-2.0.4.dist-info/WHEEL
confme-2.0.4.dist-info/RECORD
