Metadata-Version: 2.3
Name: confme
Version: 2.0.4
Summary: Easy configuration management in python
License: LICENSE
Author: Iwan Silvan Bolzern
Author-email: iwan.bolzern@roche.com
Requires-Python: >=3.8,<4.0
Classifier: Development Status :: 5 - Production/Stable
Classifier: Intended Audience :: Developers
Classifier: Intended Audience :: Healthcare Industry
Classifier: License :: OSI Approved :: MIT License
Classifier: License :: Other/Proprietary License
Classifier: Operating System :: OS Independent
Classifier: Programming Language :: Python
Classifier: Programming Language :: Python :: 3
Classifier: Programming Language :: Python :: 3.8
Classifier: Programming Language :: Python :: 3.9
Classifier: Programming Language :: Python :: 3.10
Classifier: Programming Language :: Python :: 3.11
Classifier: Programming Language :: Python :: 3.12
Classifier: Programming Language :: Python :: 3.13
Classifier: Programming Language :: Python :: 3.7
Classifier: Topic :: Software Development :: Libraries
Classifier: Topic :: Software Development :: Libraries :: Python Modules
Requires-Dist: pydantic (>=2.0,<3.0)
Requires-Dist: pyyaml (>=5.3)
Requires-Dist: tabulate (>=0.8.9)
Requires-Dist: typing-extensions (>=4.11.0,<5.0.0)
Project-URL: Homepage, https://github.com/iwanbolzern/confme
Project-URL: Repository, https://github.com/iwanbolzern/confme
